README.md
setup.py
distributions_udsp/Binomialdistribution.py
distributions_udsp/Gaussiandistribution.py
distributions_udsp/Generaldistribution.py
distributions_udsp/__init__.py
distributions_udsp.egg-info/PKG-INFO
distributions_udsp.egg-info/SOURCES.txt
distributions_udsp.egg-info/dependency_links.txt
distributions_udsp.egg-info/not-zip-safe
distributions_udsp.egg-info/top_level.txt